pyquokka/__init__.py
pyquokka/dataset.py
pyquokka/nodes.py
pyquokka/quokka_runtime.py
pyquokka/sql.py
pyquokka/state.py
pyquokka/utils.py
pyquokka_dev-0.0.2.dist-info/LICENSE
pyquokka_dev-0.0.2.dist-info/METADATA
pyquokka_dev-0.0.2.dist-info/WHEEL
pyquokka_dev-0.0.2.dist-info/top_level.txt
pyquokka_dev-0.0.2.dist-info/RECORD
