Metadata-Version: 2.1
Name: pyquokka-dev
Version: 0.0.2
Summary: Quokka
Home-page: UNKNOWN
Author: Tony Wang
Author-email: zihengw@stanford.edu
License: http://www.apache.org/licenses/LICENSE-2.0
Keywords: python
Platform: UNKNOWN
Classifier: Development Status :: 3 - Alpha
Classifier: Programming Language :: Python :: 3
Classifier: Operating System :: MacOS :: MacOS X
Classifier: Operating System :: Microsoft :: Windows
Requires-Dist: pyarrow (==6.0.1)
Requires-Dist: redis (==4.1.0)
Requires-Dist: boto3 (==1.17.24)
Requires-Dist: pandas (==1.2.2)
Requires-Dist: numpy (==1.19.2)
Requires-Dist: ray (==1.9.1)
Requires-Dist: aiobotocore
Requires-Dist: h5py
Requires-Dist: polars (==0.13.0)
